LICENSE
store_validations_oracle/__init__.py
store_validations_oracle/store_validations_oracle.py
store_validations_oracle-0.1.4.dist-info/METADATA
store_validations_oracle-0.1.4.dist-info/WHEEL
store_validations_oracle-0.1.4.dist-info/LICENSE
store_validations_oracle-0.1.4.dist-info/RECORD
