Metadata-Version: 2.1
Name: store-validations-oracle
Version: 0.1.4
Summary: Used with Great_Expectations to store validation results in an Oracle Database.
Author: Ali Bhayani
Author-email: ali@cloudshuttle.com.au
Requires-Python: >=3.8,<4.0
Classifier: License :: OSI Approved :: MIT License
Classifier: Operating System :: OS Independent
Classifier: Programming Language :: Python :: 3
Classifier: Programming Language :: Python :: 3.8
Classifier: Programming Language :: Python :: 3.9
Classifier: Programming Language :: Python :: 3.10
Classifier: Programming Language :: Python :: 3.11
Classifier: Programming Language :: Python :: 3
Requires-Dist: flatten-json (>=0.1.13,<0.2.0)
Requires-Dist: great-expectations (>=0.15.41,<0.16.0)
Requires-Dist: oracledb (>=1.2.0,<2.0.0)
Project-URL: CloudShuttle, https://www.cloudshuttle.com.au/
